Credentials_Validator/Validators.py
Credentials_Validator/__init__.py
Credentials_Validator/main.py
Credentials_Validator-0.0.4.dist-info/LICENSE
Credentials_Validator-0.0.4.dist-info/METADATA
Credentials_Validator-0.0.4.dist-info/WHEEL
Credentials_Validator-0.0.4.dist-info/top_level.txt
Credentials_Validator-0.0.4.dist-info/RECORD
