Metadata-Version: 2.1
Name: Credentials-Validator
Version: 0.0.4
Summary: Credential validation
Home-page: https://github.com/LeoneBacciu/Credentials_Validator
Author: Leone Bacciu
Author-email: leonebacciu@gmail.com
License: UNKNOWN
Platform: UNKNOWN
Classifier: Programming Language :: Python :: 3
Classifier: License :: OSI Approved :: MIT License
Classifier: Operating System :: OS Independent
Requires-Python: >=3.6
